[
  {
    "title": "Divorce หย่า (2024)",
    "image": "https://www.24-hds.com/wp-content/uploads/2024/09/Divorce-หย่า-2024.jpg",
    "episodes": [
      {
        "name": "Full Movie",
        "servers": [
          {
            "name": "EN",
            "url": "https://main.24playerhd.com/newplaylist/99a14a49593ba8b9134d2abd/2635.m3u8"
          }
        ]
      }
    ]
  },
  {
    "title": "An Invisible Victim The Eliza Samudio Case เหยื่อที่มองไม่เห็น คดีอีลิซ่า ซามูดิโอ (2024)",
    "image": "https://www.24-hds.com/wp-content/uploads/2024/09/An-Invisible-Victim-The-Eliza-Samudio-Case-เหยื่อที่มองไม่เห็น-คดีอีลิซ่า-ซามูดิโอ-2024.jpg",
    "episodes": [
      {
        "name": "Full Movie",
        "servers": [
          {
            "name": "EN",
            "url": "https://main.24playerhd.com/newplaylist/8e64d18d6e26ed1ae6a39429/9221.m3u8"
          }
        ]
      }
    ]
  },
  {
    "title": "The Princess Switch เดอะ พริ้นเซส สวิตช์ สลับตัวไม่สลับหัวใจ (2018)",
    "image": "https://www.24-hds.com/wp-content/uploads/2024/09/The-Princess-Switch-เดอะ-พริ้นเซส-สวิตช์-สลับตัวไม่สลับหัวใจ-2018.jpg",
    "episodes": [
      {
        "name": "Full Movie",
        "servers": [
          {
            "name": "TH",
            "url": "https://main.24playerhd.com/newplaylist/7ba7e5352f9901e20d1899b6/3558.m3u8"
          }
        ]
      }
    ]
  },
  {
    "title": "Sector 36 เซกเตอร์ 36 (2024)",
    "image": "https://www.24-hds.com/wp-content/uploads/2024/09/Sector-36-เซกเตอร์-36-2024.jpg",
    "episodes": [
      {
        "name": "Full Movie",
        "servers": [
          {
            "name": "TH",
            "url": "https://main.24playerhd.com/newplaylist/9feb0bc1510f635b484357fd/6232.m3u8"
          }
        ]
      }
    ]
  },
  {
    "title": "His Three Daughters สามสาว ลูกสาวพ่อ (2024)",
    "image": "https://www.24-hds.com/wp-content/uploads/2024/09/His-Three-Daughters-สามสาว-ลูกสาวพ่อ-2024.jpg",
    "episodes": [
      {
        "name": "Full Movie",
        "servers": [
          {
            "name": "EN",
            "url": "https://main.24playerhd.com/newplaylist/4c6518013d25210d6fb87675/9547.m3u8"
          }
        ]
      }
    ]
  },
  {
    "title": "Officer Black Belt เจ้าหน้าที่สายดำ (2024)",
    "image": "https://www.24-hds.com/wp-content/uploads/2024/09/Officer-Black-Belt-เจ้าหน้าที่สายดำ-2024.jpg",
    "episodes": [
      {
        "name": "Full Movie",
        "servers": [
          {
            "name": "TH",
            "url": "https://main.24playerhd.com/newplaylist/d3e0192fbcd88d7090a8e91a/5635.m3u8"
          }
        ]
      }
    ]
  },
  {
    "title": "Boxer นักชกสังเวียนดิบ (2024)",
    "image": "https://www.24-hds.com/wp-content/uploads/2024/09/Boxer-นักชกสังเวียนดิบ-2024.jpg",
    "episodes": [
      {
        "name": "Full Movie",
        "servers": [
          {
            "name": "TH",
            "url": "https://main.24playerhd.com/newplaylist/f99c7e9e6f2cbcf90638b943/3119.m3u8"
          }
        ]
      }
    ]
  },
  {
    "title": "Outlaw เจ้าแม่ (2024)",
    "image": "https://www.24-hds.com/wp-content/uploads/2024/09/Outlaw-เจ้าแม่-2024.jpg",
    "episodes": [
      {
        "name": "Full Movie",
        "servers": [
          {
            "name": "TH",
            "url": "https://main.24playerhd.com/newplaylist/2492527afd16cf717160e2ad/4053.m3u8"
          }
        ]
      }
    ]
  },
  {
    "title": "Honeymoonish (2024)",
    "image": "https://www.24-hds.com/wp-content/uploads/2024/09/Honeymoonish-2024.jpg",
    "episodes": [
      {
        "name": "Full Movie",
        "servers": [
          {
            "name": "EN",
            "url": "https://main.24playerhd.com/newplaylist/0dca3693b940b186133ce031/5651.m3u8"
          }
        ]
      }
    ]
  },
  {
    "title": "Mountain Queen The Summits of Lhakpa Sherpa ราชินีขุนเขา ลัคปา เชอร์ปา (2024)",
    "image": "https://www.24-hds.com/wp-content/uploads/2024/09/Mountain-Queen-The-Summits-of-Lhakpa-Sherpa-ราชินีขุนเขา-ลัคปา-เชอร์ปา-2024.jpg",
    "episodes": [
      {
        "name": "Full Movie",
        "servers": [
          {
            "name": "EN",
            "url": "https://main.24playerhd.com/newplaylist/8b159dc31b506fbd4aa402ae/7009.m3u8"
          }
        ]
      }
    ]
  },
  {
    "title": "Thelma the Unicorn ยูนิคอร์นน้อยเทลม่า (2024)",
    "image": "https://www.24-hds.com/wp-content/uploads/2024/09/Thelma-the-Unicorn-ยูนิคอร์นน้อยเทลม่า-2024.jpg",
    "episodes": [
      {
        "name": "Full Movie",
        "servers": [
          {
            "name": "EN",
            "url": "https://main.24playerhd.com/newplaylist/edc968c991bee195b8115189/4206.m3u8"
          }
        ]
      }
    ]
  },
  {
    "title": "Apollo 13 Survival อะพอลโล 13 ภารกิจต้องรอด (2024)",
    "image": "https://www.24-hds.com/wp-content/uploads/2024/09/Apollo-13-Survival-อะพอลโล-13-ภารกิจต้องรอด-2024.jpg",
    "episodes": [
      {
        "name": "Full Movie",
        "servers": [
          {
            "name": "EN",
            "url": "https://main.24playerhd.com/newplaylist/152855e12fd6f74b7b95b1e4/5360.m3u8"
          }
        ]
      }
    ]
  },
  {
    "title": "Secret Lives of Orangutans ชีวิตลับอุรังอุตัง (2024)",
    "image": "https://www.24-hds.com/wp-content/uploads/2024/09/Secret-Lives-of-Orangutans-ชีวิตลับอุรังอุตัง-2024.jpg",
    "episodes": [
      {
        "name": "Full Movie",
        "servers": [
          {
            "name": "EN",
            "url": "https://main.24playerhd.com/newplaylist/f91a51651d12de97a9ab7040/4910.m3u8"
          }
        ]
      }
    ]
  },
  {
    "title": "Tokunbo โทคุนโบ (2024)",
    "image": "https://www.24-hds.com/wp-content/uploads/2024/09/Tokunbo-Tokunbo̩-โทคุนโบ-2024.jpg",
    "episodes": [
      {
        "name": "Full Movie",
        "servers": [
          {
            "name": "EN",
            "url": "https://main.24playerhd.com/newplaylist/8af6061da036bb5cf75ebb37/5620.m3u8"
          }
        ]
      }
    ]
  },
  {
    "title": "Nice Girls (2024)",
    "image": "https://www.24-hds.com/wp-content/uploads/2024/09/Nice-Girls-2024.jpg",
    "episodes": [
      {
        "name": "Full Movie",
        "servers": [
          {
            "name": "TH",
            "url": "https://main.24playerhd.com/newplaylist/b1bd5b511e46ae1509d71b08/8404.m3u8"
          }
        ]
      }
    ]
  },
  {
    "title": "Incoming มือใหม่ไฮสกูล (2024)",
    "image": "https://www.24-hds.com/wp-content/uploads/2024/09/Incoming-มือใหม่ไฮสกูล-2024.jpg",
    "episodes": [
      {
        "name": "Full Movie",
        "servers": [
          {
            "name": "TH",
            "url": "https://main.24playerhd.com/newplaylist/113fbe62869a458769b605db/1486.m3u8"
          }
        ]
      }
    ]
  },
  {
    "title": "Rebel Ridge เรเบลริดจ์ ผ่าเมืองอยุติธรรม (2024)",
    "image": "https://www.24-hds.com/wp-content/uploads/2024/09/Rebel-Ridge-เรเบลริดจ์-ผ่าเมืองอยุติธรรม-2024.jpg",
    "episodes": [
      {
        "name": "Full Movie",
        "servers": [
          {
            "name": "TH",
            "url": "https://main.24playerhd.com/newplaylist/fa42b12851ac746b34e96279/9836.m3u8"
          }
        ]
      }
    ]
  },
  {
    "title": "The Deliverance บ้านปลดวิญญาณ (2024)",
    "image": "https://www.24-hds.com/wp-content/uploads/2024/09/The-Deliverance-บ้านปลดวิญญาณ-2024.jpg",
    "episodes": [
      {
        "name": "Full Movie",
        "servers": [
          {
            "name": "EN",
            "url": "https://main.24playerhd.com/newplaylist/e004fe6df9845b9e1cd999e9/3938.m3u8"
          }
        ]
      }
    ]
  },
  {
    "title": "(Un)lucky Sisters โชค(ไม่)ดี พี่กับน้อง (2024)",
    "image": "https://www.24-hds.com/wp-content/uploads/2024/09/Unlucky-Sisters-โชคไม่ดี-พี่กับน้อง-2024.jpg",
    "episodes": [
      {
        "name": "Full Movie",
        "servers": [
          {
            "name": "EN",
            "url": "https://main.24playerhd.com/newplaylist/001770d03b8c5a888439af82/8439.m3u8"
          }
        ]
      }
    ]
  },
  {
    "title": "Rebel ขบถ (2024)",
    "image": "https://www.24-hds.com/wp-content/uploads/2024/09/Rebel-ขบถ-2024.jpg",
    "episodes": [
      {
        "name": "Full Movie",
        "servers": [
          {
            "name": "EN",
            "url": "https://main.24playerhd.com/newplaylist/089db13cdd5224ae384071c2/4078.m3u8"
          }
        ]
      }
    ]
  },
  {
    "title": "Sheriff: Narko Integriti มือปราบเจ้าพ่อเถื่อน (2024)",
    "image": "https://www.24-hds.com/wp-content/uploads/2024/09/Sheriff-Narko-Integriti-มือปราบเจ้าพ่อเถื่อน-2024-.jpg",
    "episodes": [
      {
        "name": "Full Movie",
        "servers": [
          {
            "name": "EN",
            "url": "https://main.24playerhd.com/newplaylist/06c628bff1b3251cbe02c566/7387.m3u8"
          }
        ]
      }
    ]
  },
  {
    "title": "Untold: Sign Stealer คนขโมยสัญญาณมือ (2024)",
    "image": "https://www.24-hds.com/wp-content/uploads/2024/09/Untold-Sign-Stealer-คนขโมยสัญญาณมือ-2024.png",
    "episodes": [
      {
        "name": "Full Movie",
        "servers": [
          {
            "name": "EN",
            "url": "https://main.24playerhd.com/newplaylist/e43c2776d8c26a1d40dcc8c9/1488.m3u8"
          }
        ]
      }
    ]
  },
  {
    "title": "The Union (2024) เดอะ ยูเนี่ยน",
    "image": "https://www.24-hds.com/wp-content/uploads/2024/08/The-Union-2024.jpg",
    "episodes": [
      {
        "name": "Full Movie",
        "servers": [
          {
            "name": "TH",
            "url": "https://main.24playerhd.com/newplaylist/3b6046c367563f6a1e8d9ed9/9617.m3u8"
          },
          {
            "name": "EN",
            "url": "https://main.24playerhd.com/newplaylist/18d055908ece4bc558df28b3/3825.m3u8"
          }
        ]
      }
    ]
  },
  {
    "title": "Daughters (2024)",
    "image": "https://www.24-hds.com/wp-content/uploads/2024/08/Daughters-2024.jpg",
    "episodes": [
      {
        "name": "Full Movie",
        "servers": [
          {
            "name": "EN",
            "url": "https://main.24playerhd.com/newplaylist/8ce7ac08a193686334c823e4/7377.m3u8"
          }
        ]
      }
    ]
  },
  {
    "title": "May December (2023) รัก ร่าน ร้าย",
    "image": "https://www.24-hds.com/wp-content/uploads/2024/08/May-December-2023-รัก-ร่าน-ร้าย-1.jpg",
    "episodes": [
      {
        "name": "Full Movie",
        "servers": [
          {
            "name": "TH",
            "url": "https://main.24playerhd.com/newplaylist/433c2edfb2891cb6621f0ebb/1493.m3u8"
          },
          {
            "name": "EN",
            "url": "https://main.24playerhd.com/newplaylist/9229105ddb45f20cdfc82d30/8578.m3u8"
          }
        ]
      }
    ]
  },
  {
    "title": "Inside the Mind of a Dog (2024) อ่านใจสุนัข",
    "image": "https://www.24-hds.com/wp-content/uploads/2024/08/Inside-the-Mind-of-a-Dog-2024-อ่านใจสุนัข.jpg",
    "episodes": [
      {
        "name": "Full Movie",
        "servers": [
          {
            "name": "TH",
            "url": "https://main.24playerhd.com/newplaylist/757e551de0ffd8374239eb37/9968.m3u8"
          },
          {
            "name": "EN",
            "url": "https://main.24playerhd.com/newplaylist/6fb88c4c42f0bbb6e0fef79d/4584.m3u8"
          }
        ]
      }
    ]
  },
  {
    "title": "Phir Aayi Hasseen Dillruba (2024) กุหลาบมรณะ 2",
    "image": "https://www.24-hds.com/wp-content/uploads/2024/08/Phir-Aayi-Hasseen-Dillruba-2024-กุหลาบมรณะ-2.jpg",
    "episodes": [
      {
        "name": "Full Movie",
        "servers": [
          {
            "name": "EN",
            "url": "https://main.24playerhd.com/newplaylist/6f7888a60f728897f2eacc6d/8873.m3u8"
          }
        ]
      }
    ]
  },
  {
    "title": "Mission Cross (2024) ภารกิจลับพ่อบ้าน",
    "image": "https://www.24-hds.com/wp-content/uploads/2024/08/Mission-Cross-2024-ภารกิจลับพ่อบ้าน.jpg",
    "episodes": [
      {
        "name": "Full Movie",
        "servers": [
          {
            "name": "TH",
            "url": "https://main.24playerhd.com/newplaylist/1632b9083748a0e71eb4d6a7/4510.m3u8"
          },
          {
            "name": "EN",
            "url": "https://main.24playerhd.com/newplaylist/61b93be3a407adf77a3cc3cc/5119.m3u8"
          }
        ]
      }
    ]
  },
  {
    "title": "Lolo and the Kid (2024) โลโล่ แอนด์ เดอะ คิด",
    "image": "https://www.24-hds.com/wp-content/uploads/2024/08/Lolo-and-the-Kid-2024-โลโล่-แอนด์-เดอะ-คิด.jpg",
    "episodes": [
      {
        "name": "Full Movie",
        "servers": [
          {
            "name": "EN",
            "url": "https://main.24playerhd.com/newplaylist/2ce2b7a278b3291dac366fa7/5949.m3u8"
          }
        ]
      }
    ]
  },
  {
    "title": "Godzilla Minus One (2023) Minus Color",
    "image": "https://www.24-hds.com/wp-content/uploads/2024/08/Godzilla-Minus-One-2023-Minus-Color-1.jpg",
    "episodes": [
      {
        "name": "Full Movie",
        "servers": [
          {
            "name": "TH",
            "url": "https://main.24playerhd.com/newplaylist/4b026d2c78ff2a915849e1ba/1697.m3u8"
          },
          {
            "name": "EN",
            "url": "https://main.24playerhd.com/newplaylist/687070984a202a64ff5a9ba2/3101.m3u8"
          }
        ]
      }
    ]
  },
  {
    "title": "Rebel Moon Part Two A Director’s Cut (2024)",
    "image": "https://www.24-hds.com/wp-content/uploads/2024/08/Rebel-Moon-Part-Two-A-Directors-Cut-2024.jpg",
    "episodes": [
      {
        "name": "Full Movie",
        "servers": [
          {
            "name": "TH",
            "url": "https://main.24playerhd.com/newplaylist/c826bc7000f674c32455d809/8727.m3u8"
          },
          {
            "name": "EN",
            "url": "https://main.24playerhd.com/newplaylist/efd12dc99f072cbbe1a264cf/3390.m3u8"
          }
        ]
      }
    ]
  },
  {
    "title": "Rebel Moon Part One A Director’s Cut (2024)",
    "image": "https://www.24-hds.com/wp-content/uploads/2024/08/Rebel-Moon-Part-One-A-Directors-Cut-2024.jpg",
    "episodes": [
      {
        "name": "Full Movie",
        "servers": [
          {
            "name": "TH",
            "url": "https://main.24playerhd.com/newplaylist/d1ccc983190d22ef8ffa96c3/8904.m3u8"
          },
          {
            "name": "EN",
            "url": "https://main.24playerhd.com/newplaylist/0108c6bedcebddf405b43ffa/8880.m3u8"
          }
        ]
      }
    ]
  },
  {
    "title": "Saving Bikini Bottom The Sandy Cheeks Movie (2024)",
    "image": "https://www.24-hds.com/wp-content/uploads/2024/08/Saving-Bikini-Bottom-The-Sandy-Cheeks-Movie-2024.jpg",
    "episodes": [
      {
        "name": "Full Movie",
        "servers": [
          {
            "name": "TH",
            "url": "https://main.24playerhd.com/newplaylist/708af05f09dd62b42394ef3a/1906.m3u8"
          },
          {
            "name": "EN",
            "url": "https://main.24playerhd.com/newplaylist/d45e4ffa673211dfb96b4507/7465.m3u8"
          }
        ]
      }
    ]
  },
  {
    "title": "Modern Masters (2024) ปรมาจารย์ยุคใหม่ เอสเอส ราจามูลี",
    "image": "https://www.24-hds.com/wp-content/uploads/2024/08/Modern-Masters-2024-ปรมาจารย์ยุคใหม่-เอสเอส-ราจามูลี.jpg",
    "episodes": [
      {
        "name": "Full Movie",
        "servers": [
          {
            "name": "EN",
            "url": "https://main.24playerhd.com/newplaylist/c93989993ca0d13483224944/3172.m3u8"
          }
        ]
      }
    ]
  },
  {
    "title": "Borderless Fog (2024) หมอกไร้พรมแดน",
    "image": "https://www.24-hds.com/wp-content/uploads/2024/08/Borderless-Fog-2024-หมอกไร้พรมแดน.jpg",
    "episodes": [
      {
        "name": "Full Movie",
        "servers": [
          {
            "name": "EN",
            "url": "https://main.24playerhd.com/newplaylist/abd338f1a8c0ecf62651b0ff/8519.m3u8"
          }
        ]
      }
    ]
  },
  {
    "title": "Mon Laferte (2024) ฉันรักเธอ",
    "image": "https://www.24-hds.com/wp-content/uploads/2024/08/Mon-Laferte-2024-ฉันรักเธอ.jpg",
    "episodes": [
      {
        "name": "Full Movie",
        "servers": [
          {
            "name": "EN",
            "url": "https://main.24playerhd.com/newplaylist/d0daf0d4806862f201530a1b/3176.m3u8"
          }
        ]
      }
    ]
  },
  {
    "title": "The Cursed (2024) เหมรฺย",
    "image": "https://www.24-hds.com/wp-content/uploads/2024/07/The-Cursed-2024-เหมรฺย-1.jpg",
    "episodes": [
      {
        "name": "Full Movie",
        "servers": [
          {
            "name": "TH",
            "url": "https://main.24playerhd.com/newplaylist/dcc8921a64a9e1af57fbf3da/1130.m3u8"
          }
        ]
      }
    ]
  },
  {
    "title": "Wonderland (2024) วันเดอร์แลนด์",
    "image": "https://www.24-hds.com/wp-content/uploads/2024/07/Wonderland-2024-วันเดอร์แลนด์.jpg",
    "episodes": [
      {
        "name": "Full Movie",
        "servers": [
          {
            "name": "TH",
            "url": "https://main.24playerhd.com/newplaylist/bed4a42f112b0d99d2b7069e/3164.m3u8"
          }
        ]
      }
    ]
  },
  {
    "title": "Non Negotiable (2024) เจรจาท้ารัก",
    "image": "https://www.24-hds.com/wp-content/uploads/2024/07/Non-Negotiable-2024-เจรจาท้ารัก.jpg",
    "episodes": [
      {
        "name": "Full Movie",
        "servers": [
          {
            "name": "EN",
            "url": "https://main.24playerhd.com/newplaylist/ffeea4710f85900932d9143c/6700.m3u8"
          }
        ]
      }
    ]
  },
  {
    "title": "House of Ga'a (2024) บัลลังก์แห่งกาอา",
    "image": "https://www.24-hds.com/wp-content/uploads/2024/07/House-of-Gaa-2024-บัลลังก์แห่งกาอา.jpg",
    "episodes": [
      {
        "name": "Full Movie",
        "servers": [
          {
            "name": "EN",
            "url": "https://main.24playerhd.com/newplaylist/2f6ff181beaebf78733b844d/6794.m3u8"
          }
        ]
      }
    ]
  }
]