[
  {
    "title": "Meet the Khumalos (2025) เปิดบ้านป่วนคูมาโล",
    "link": "https://www.24-hds.com/meet-the-khumalos/",
    "image": "https://www.24-hds.com/wp-content/uploads/2025/04/Meet-the-Khumalos-2025-เปิดบ้านป่วนคูมาโล.png",
    "episodes": [
      {
        "name": "Full Movie",
        "servers": [
          {
            "name": "EN",
            "url": "https://main.24playerhd.com/newplaylist/804c5842a7e7ae4445cca2f5/7742.m3u8"
          }
        ]
      }
    ]
  },
  {
    "title": "Alien Rubicon (2024)",
    "link": "https://www.24-hds.com/alien-rubicon/",
    "image": "https://www.24-hds.com/wp-content/uploads/2025/04/Alien-Rubicon-2024.png",
    "episodes": [
      {
        "name": "Full Movie",
        "servers": [
          {
            "name": "EN",
            "url": "https://main.24playerhd.com/newplaylist/ad031b3ccf5ec8fd324a4852/1361.m3u8"
          }
        ]
      }
    ]
  },
  {
    "title": "How to Be Really Bad (2018) ภารกิจแสบแบบฉบับนรก",
    "link": "https://www.24-hds.com/how-to-be-really-bad/",
    "image": "https://www.24-hds.com/wp-content/uploads/2023/06/How-to-Be-Really-Bad-2018-ภารกิจแสบแบบฉบับนรก.jpg",
    "episodes": [
      {
        "name": "Full Movie",
        "servers": [
          {
            "name": "EN",
            "url": "https://main.24playerhd.com/newplaylist/ed11309e0561a3f9f9bcf9a3/9911.m3u8"
          }
        ]
      }
    ]
  },
  {
    "title": "How to Succeed at Losing (2023) ครั้งนี้ขอกลับมาปัง",
    "link": "https://www.24-hds.com/how-to-succeed-at-losing/",
    "image": "https://www.24-hds.com/wp-content/uploads/2024/01/How-to-Succeed-at-Losing-2023-ครั้งนี้ขอกลับมาปัง.jpg",
    "episodes": [
      {
        "name": "Full Movie",
        "servers": [
          {
            "name": "EN",
            "url": "https://main.24playerhd.com/newplaylist/3d6cce285dad64f5da915c53/8576.m3u8"
          }
        ]
      }
    ]
  },
  {
    "title": "How to Rob a Bank (2024) คู่มือปล้นแบงก์",
    "link": "https://www.24-hds.com/how-to-rob-a-bank/",
    "image": "https://www.24-hds.com/wp-content/uploads/2024/06/How-to-Rob-a-Bank-2024-คู่มือปล้นแบงก์.jpg",
    "episodes": [
      {
        "name": "Full Movie",
        "servers": [
          {
            "name": "EN",
            "url": "https://main.24playerhd.com/newplaylist/a186bf6f5c9ce62e0fe280f6/8195.m3u8"
          }
        ]
      }
    ]
  },
  {
    "title": "How To Have Sex (2023) ซิงนั้นสำคัญไฉน",
    "link": "https://www.24-hds.com/how-to-have-sex/",
    "image": "https://www.24-hds.com/wp-content/uploads/2024/02/How-To-Have-Sex-2023-ซิงนั้นสำคัญไฉน.jpg",
    "episodes": [
      {
        "name": "Full Movie",
        "servers": [
          {
            "name": "TH",
            "url": "https://main.24playerhd.com/newplaylist/f843824bfbe6f2a0a07924a6/6741.m3u8"
          },
          {
            "name": "EN",
            "url": "https://main.24playerhd.com/newplaylist/5efccb4c637e4e0e75fddf8d/4965.m3u8"
          }
        ]
      }
    ]
  },
  {
    "title": "Conjuring the Beyond (2022)",
    "link": "https://www.24-hds.com/conjuring-the-beyond/",
    "image": "https://www.24-hds.com/wp-content/uploads/2023/01/Conjuring-the-Beyond-2022.jpg",
    "episodes": [
      {
        "name": "Full Movie",
        "servers": [
          {
            "name": "EN",
            "url": "https://main.24playerhd.com/newplaylist/5c51fec03e84c04eaedc284b/5354.m3u8"
          }
        ]
      }
    ]
  },
  {
    "title": "The Conjuring (2013) เดอะ คอนเจอริ่ง คนเรียกผี",
    "link": "https://www.24-hds.com/the-conjuring-%e0%b8%a0%e0%b8%b2%e0%b8%84-1/",
    "image": "http://www.24-hdmovie.com/wp-content/uploads/2023/01/The-Conjuring-2013-เดอะ-คอนเจอริ่ง-คนเรียกผี.jpg",
    "episodes": [
      {
        "name": "Full Movie",
        "servers": [
          {
            "name": "TH",
            "url": "https://main.24playerhd.com/newplaylist/37695815e858f5116b8c41ca/2843.m3u8"
          },
          {
            "name": "EN",
            "url": "https://main.24playerhd.com/newplaylist/3ceb0c7c21f3d8d5b7ba5cab/1262.m3u8"
          }
        ]
      }
    ]
  },
  {
    "title": "The Conjuring 2 (2016) เดอะ คอนเจอริ่ง คนเรียกผี 2",
    "link": "https://www.24-hds.com/the-conjuring-%e0%b8%a0%e0%b8%b2%e0%b8%84-2/",
    "image": "http://www.24-hdmovie.com/wp-content/uploads/2023/01/The-Conjuring-2-2016-เดอะ-คอนเจอริ่ง-คนเรียกผี-2.jpg",
    "episodes": [
      {
        "name": "Full Movie",
        "servers": [
          {
            "name": "TH",
            "url": "https://main.24playerhd.com/newplaylist/9820065c36234bd3f1b740f1/3633.m3u8"
          },
          {
            "name": "EN",
            "url": "https://main.24playerhd.com/newplaylist/b6df60a078d1189090e028a2/9159.m3u8"
          }
        ]
      }
    ]
  },
  {
    "title": "The Conjuring 3 The Devil Made Me Do It (2021) เดอะ คอนเจอริ่ง คนเรียกผี 3",
    "link": "https://www.24-hds.com/the-conjuring-%e0%b8%a0%e0%b8%b2%e0%b8%84-3/",
    "image": "http://www.24-hdmovie.com/wp-content/uploads/2023/01/The-Conjuring-3.jpg",
    "episodes": [
      {
        "name": "Full Movie",
        "servers": [
          {
            "name": "TH",
            "url": "https://main.24playerhd.com/newplaylist/dac98a7b1bb991c3d4b23641/3604.m3u8"
          },
          {
            "name": "EN",
            "url": "https://main.24playerhd.com/newplaylist/666a9de0cb4d50c4e6c933e6/5111.m3u8"
          }
        ]
      }
    ]
  },
  {
    "title": "The Moogai (2024) ผีลักลูกคน",
    "link": "https://www.24-hds.com/the-moogai/",
    "image": "https://www.24-hds.com/wp-content/uploads/2025/04/The-Moogai-2024-ผีลักลูกคน.png",
    "episodes": [
      {
        "name": "Full Movie",
        "servers": [
          {
            "name": "TH",
            "url": "https://main.24playerhd.com/newplaylist/de2e5cbcf32b29d5c079250d/8497.m3u8"
          }
        ]
      }
    ]
  },
  {
    "title": "Mickey 17 (2025) มิกกี้ 17",
    "link": "https://www.24-hds.com/mickey-17/",
    "image": "https://www.24-hds.com/wp-content/uploads/2025/03/Mickey-17-2025-มิกกี้-17.png",
    "episodes": [
      {
        "name": "Full Movie",
        "servers": [
          {
            "name": "TH",
            "url": "https://main.24playerhd.com/newplaylist/d30288ae796ac9aed3bb6485/2366.m3u8"
          },
          {
            "name": "EN",
            "url": "https://main.24playerhd.com/newplaylist/31fe99495ed273881b1bdf61/9724.m3u8"
          }
        ]
      }
    ]
  },
  {
    "title": "iHostage (2025) จับตัวประกันสนั่นเมือง",
    "link": "https://www.24-hds.com/ihostage/",
    "image": "https://www.24-hds.com/wp-content/uploads/2025/04/iHostage-2025-จับตัวประกันสนั่นเมือง.png",
    "episodes": [
      {
        "name": "Full Movie",
        "servers": [
          {
            "name": "TH",
            "url": "https://main.24playerhd.com/newplaylist/83e93aa732ff119e593269f4/1147.m3u8"
          },
          {
            "name": "EN",
            "url": "https://main.24playerhd.com/newplaylist/9cc086dd339dc4539e82547f/6094.m3u8"
          }
        ]
      }
    ]
  },
  {
    "title": "Jungle (2017) แดนฝันป่านรก",
    "link": "https://www.24-hds.com/jungle/",
    "image": "https://www.24-hds.com/wp-content/uploads/2025/04/Jungle-2017.png",
    "episodes": [
      {
        "name": "Full Movie",
        "servers": [
          {
            "name": "TH",
            "url": "https://main.24playerhd.com/newplaylist/130331b086dfe8a2b2a7bb36/6164.m3u8"
          },
          {
            "name": "EN",
            "url": "https://main.24playerhd.com/newplaylist/9da67c1594d17af5b97c0b31/4040.m3u8"
          }
        ]
      }
    ]
  },
  {
    "title": "High Life (2018)",
    "link": "https://www.24-hds.com/high-life/",
    "image": "https://www.24-hds.com/wp-content/uploads/2025/04/High-Life-2018.png",
    "episodes": [
      {
        "name": "Full Movie",
        "servers": [
          {
            "name": "EN",
            "url": "https://main.24playerhd.com/newplaylist/8a6201e31519f33b86f04e78/2198.m3u8"
          }
        ]
      }
    ]
  },
  {
    "title": "Reversi (2024) รีเวอร์ซี่ ย้อนชีวิตพลิกชะตา",
    "link": "https://www.24-hds.com/reversi/",
    "image": "https://www.24-hds.com/wp-content/uploads/2025/04/Reversi-2024-รีเวอร์ซี่-ย้อนชีวิตพลิกชะตา.png",
    "episodes": [
      {
        "name": "Full Movie",
        "servers": [
          {
            "name": "EN",
            "url": "https://main.24playerhd.com/newplaylist/9ec180d1303e92cef7027681/4995.m3u8"
          }
        ]
      }
    ]
  },
  {
    "title": "Take Cover (2024)",
    "link": "https://www.24-hds.com/take-cover/",
    "image": "https://www.24-hds.com/wp-content/uploads/2025/04/Take-Cover-2024.png",
    "episodes": [
      {
        "name": "Full Movie",
        "servers": [
          {
            "name": "EN",
            "url": "https://main.24playerhd.com/newplaylist/0278423349113f806db76d50/4853.m3u8"
          }
        ]
      }
    ]
  },
  {
    "title": "The Burning Sea (2021) มหาวิบัติหายนะทะเลเพลิง",
    "link": "https://www.24-hds.com/the-burning-sea/",
    "image": "https://www.24-hds.com/wp-content/uploads/2023/06/The-Burning-Sea-2021-มหาวิบัติหายนะทะเลเพลิง.jpg",
    "episodes": [
      {
        "name": "Full Movie",
        "servers": [
          {
            "name": "TH",
            "url": "https://main.24playerhd.com/newplaylist/7730d81938ae7e03eb61061b/3723.m3u8"
          },
          {
            "name": "EN",
            "url": "https://main.24playerhd.com/newplaylist/17ad65085ba184a6bce7cb67/5622.m3u8"
          }
        ]
      }
    ]
  },
  {
    "title": "Woman of the Hour (2023) รู้ไหมใครโหด",
    "link": "https://www.24-hds.com/woman-of-the-hour/",
    "image": "https://www.24-hds.com/wp-content/uploads/2025/04/Woman-of-the-Hour-2023-รู้ไหมใครโหด.png",
    "episodes": [
      {
        "name": "Full Movie",
        "servers": [
          {
            "name": "TH",
            "url": "https://main.24playerhd.com/newplaylist/054fb266f89f52ab33622519/7716.m3u8"
          },
          {
            "name": "EN",
            "url": "https://main.24playerhd.com/newplaylist/4b63018aca1ad19ab53677ba/1872.m3u8"
          }
        ]
      }
    ]
  },
  {
    "title": "The 33 (2015) 33 ใต้นรก 200 ชั้น",
    "link": "https://www.24-hds.com/the-33/",
    "image": "https://www.24-hds.com/wp-content/uploads/2023/05/The-33-2015-33-ใต้นรก-200-ชั้น.jpg",
    "episodes": [
      {
        "name": "Full Movie",
        "servers": [
          {
            "name": "EN",
            "url": "https://main.m3u8p.com/?id=Failed to connect to MySQL - Too many connections"
          }
        ]
      }
    ]
  }
]